warp10/__init__.py
warp10/app.py
warp10/client.py
warp10/element.py
warp10/pipeline.py
warp10/protocol.py
warp10-0.1.1.dist-info/WHEEL
warp10-0.1.1.dist-info/METADATA
warp10-0.1.1.dist-info/RECORD
