Metadata-Version: 2.1
Name: warp10
Version: 0.1.1
Summary: SPA Framework
Author: Zeb
Author-email: zceboys@gmail.com
Requires-Python: >=3.8.0,<3.11
Classifier: Programming Language :: Python :: 3
Classifier: Programming Language :: Python :: 3.10
Classifier: Programming Language :: Python :: 3.8
Classifier: Programming Language :: Python :: 3.9
Requires-Dist: Flask (>=2.2.0,<3.0.0)
Requires-Dist: numpy (>=1.22.2,<2.0.0)
Requires-Dist: replit (>=3.2.4,<4.0.0)
Requires-Dist: sanic (>=22.6.2,<23.0.0)
Requires-Dist: toml (>=0.10.2,<0.11.0)
